Workbook

Sheet Transactions
A1: Date | B1: Type | C1: Category | D1: Description | E1: Amount | F1: Payment Method
A2: 46023 | B2: Income | C2: Salary | D2: Monthly salary | E2: 45000 | F2: Bank
A3: 46024 | B3: Expense | C3: Rent | D3: Monthly rent | E3: 12000 | F3: Bank
A4: 46025 | B4: Expense | C4: Food | D4: Groceries | E4: 3500 | F4: M-Pesa
A5: 46026 | B5: Expense | C5: Transport | D5: Transport | E5: 1200 | F5: M-Pesa
A6: 46027 | B6: Expense | C6: Airtime & Data | D6: Internet bundle | E6: 1000 | F6: M-Pesa
A7: 46030 | B7: Expense | C7: Utilities | D7: Electricity | E7: 1800 | F7: M-Pesa
A8: 46034 | B8: Expense | C8: Education | D8: Course materials | E8: 2500 | F8: M-Pesa
A9: 46037 | B9: Expense | C9: Family | D9: Family support | E9: 3000 | F9: Bank
A10: 46042 | B10: Expense | C10: Food | D10: Eating out | E10: 1500 | F10: M-Pesa
A11: 46047 | B11: Savings | C11: Savings/Investment | D11: Savings deposit | E11: 5000 | F11: Bank
A12: 46054 | B12: Income | C12: Salary | D12: Monthly salary | E12: 45000 | F12: Bank
A13: 46055 | B13: Expense | C13: Rent | D13: Monthly rent | E13: 12000 | F13: Bank
... A61: 46201 | B61: Savings | C61: Savings/Investment | D61: Savings deposit | E61: 7500 | F61: Bank

Sheet Analysis
A1: Personal Finance Analysis
A3: Metric | B3: Value | D3: Expense Category | E3: Total | F3: Expense %
A4: Total Income | B4: =SUMIF(Transactions!B:B,"Income",Transactions!E:E) -> 270000 | D4: Rent | E4: =SUMIFS(Transactions!E:E,Transactions!C:C,D4,Transactions!B:B,"Expense") -> 72000 | F4: =E4/$B$5 -> 0.42427814
A5: Total Expenses | B5: =SUMIF(Transactions!B:B,"Expense",Transactions!E:E) -> 169700 | D5: Food | E5: =SUMIFS(Transactions!E:E,Transactions!C:C,D5,Transactions!B:B,"Expense") -> 26300 | F5: =E5/$B$5 -> 0.15497938
A6: Total Savings | B6: =SUMIF(Transactions!B:B,"Savings",Transactions!E:E) -> 39000 | D6: Transport | E6: =SUMIFS(Transactions!E:E,Transactions!C:C,D6,Transactions!B:B,"Expense") -> 9700 | F6: =E6/$B$5 -> 0.057159694
A7: Net Cash Flow | B7: =B4-B5-B6 -> 61300 | D7: Airtime & Data | E7: =SUMIFS(Transactions!E:E,Transactions!C:C,D7,Transactions!B:B,"Expense") -> 6600 | F7: =E7/$B$5 -> 0.038892163
A8: Savings Rate | B8: =B6/B4 -> 0.14444444 | D8: Utilities | E8: =SUMIFS(Transactions!E:E,Transactions!C:C,D8,Transactions!B:B,"Expense") -> 10800 | F8: =E8/$B$5 -> 0.063641721
D9: Education | E9: =SUMIFS(Transactions!E:E,Transactions!C:C,D9,Transactions!B:B,"Expense") -> 10800 | F9: =E9/$B$5 -> 0.063641721
D10: Family | E10: =SUMIFS(Transactions!E:E,Transactions!C:C,D10,Transactions!B:B,"Expense") -> 18500 | F10: =E10/$B$5 -> 0.10901591
D11: Health | E11: =SUMIFS(Transactions!E:E,Transactions!C:C,D11,Transactions!B:B,"Expense") -> 4300 | F11: =E11/$B$5 -> 0.025338833
D12: Entertainment | E12: =SUMIFS(Transactions!E:E,Transactions!C:C,D12,Transactions!B:B,"Expense") -> 6000 | F12: =E12/$B$5 -> 0.035356511
D13: Shopping | E13: =SUMIFS(Transactions!E:E,Transactions!C:C,D13,Transactions!B:B,"Expense") -> 4700 | F13: =E13/$B$5 -> 0.027695934
A16: A | B16: B | C16: C | D16: D | E16: E
A17: Month | B17: Income | C17: Expenses | D17: Savings | E17: Net Cash Flow | F17: Savings Rate
A18: January | B18: =SUMIFS(Transactions!E:E,Transactions!B:B,"Income",Transactions!A:A,">="&DATE(2026,1,1),Transactions!A:A,"<="&DATE(2026,1,31)) -> 45000 | C18: =SUMIFS(Transactions!E:E,Transactions!B:B,"Expense",Transactions!A:A,">="&DATE(2026,1,1),Transactions!A:A,"<"&DATE(2026,2,1)) -> 26500 | D18: =SUMIFS(Transactions!E:E,Transactions!B:B,"Savings",Transactions!A:A,">="&DATE(2026,1,1),Transactions!A:A,"<"&DATE(2026,2,1)) -> 5000 | E18: =B18-C18-D18 -> 13500 | F18: =D18/B18 -> 0.11111111
A19: February | B19: =SUMIFS(Transactions!E:E,Transactions!B:B,"Income",Transactions!A:A,">="&DATE(2026,ROW()-17,1),Transactions!A:A,"<"&DATE(2026,ROW()-16,1)) -> 45000 | C19: =SUMIFS(Transactions!E:E,Transactions!B:B,"Expense",Transactions!A:A,">="&DATE(2026,ROW()-17,1),Transactions!A:A,"<"&DATE(2026,ROW()-16,1)) -> 27800 | D19: =SUMIFS(Transactions!E:E,Transactions!B:B,"Savings",Transactions!A:A,">="&DATE(2026,ROW()-17,1),Transactions!A:A,"<"&DATE(2026,ROW()-16,1)) -> 6000 | E19: =B19-C19-D19 -> 11200 | F19: =D19/B19 -> 0.13333333
A20: March | B20: =SUMIFS(Transactions!E:E,Transactions!B:B,"Income",Transactions!A:A,">="&DATE(2026,ROW()-17,1),Transactions!A:A,"<"&DATE(2026,ROW()-16,1)) -> 45000 | C20: =SUMIFS(Transactions!E:E,Transactions!B:B,"Expense",Transactions!A:A,">="&DATE(2026,ROW()-17,1),Transactions!A:A,"<"&DATE(2026,ROW()-16,1)) -> 28200 | D20: =SUMIFS(Transactions!E:E,Transactions!B:B,"Savings",Transactions!A:A,">="&DATE(2026,ROW()-17,1),Transactions!A:A,"<"&DATE(2026,ROW()-16,1)) -> 7000 | E20: =B20-C20-D20 -> 9800 | F20: =D20/B20 -> 0.15555556
A21: April | B21: =SUMIFS(Transactions!E:E,Transactions!B:B,"Income",Transactions!A:A,">="&DATE(2026,ROW()-17,1),Transactions!A:A,"<"&DATE(2026,ROW()-16,1)) -> 45000 | C21: =SUMIFS(Transactions!E:E,Transactions!B:B,"Expense",Transactions!A:A,">="&DATE(2026,ROW()-17,1),Transactions!A:A,"<"&DATE(2026,ROW()-16,1)) -> 29300 | D21: =SUMIFS(Transactions!E:E,Transactions!B:B,"Savings",Transactions!A:A,">="&DATE(2026,ROW()-17,1),Transactions!A:A,"<"&DATE(2026,ROW()-16,1)) -> 6500 | E21: =B21-C21-D21 -> 9200 | F21: =D21/B21 -> 0.14444444
A22: May | B22: =SUMIFS(Transactions!E:E,Transactions!B:B,"Income",Transactions!A:A,">="&DATE(2026,ROW()-17,1),Transactions!A:A,"<"&DATE(2026,ROW()-16,1)) -> 45000 | C22: =SUMIFS(Transactions!E:E,Transactions!B:B,"Expense",Transactions!A:A,">="&DATE(2026,ROW()-17,1),Transactions!A:A,"<"&DATE(2026,ROW()-16,1)) -> 27800 | D22: =SUMIFS(Transactions!E:E,Transactions!B:B,"Savings",Transactions!A:A,">="&DATE(2026,ROW()-17,1),Transactions!A:A,"<"&DATE(2026,ROW()-16,1)) -> 7000 | E22: =B22-C22-D22 -> 10200 | F22: =D22/B22 -> 0.15555556
A23: June | B23: =SUMIFS(Transactions!E:E,Transactions!B:B,"Income",Transactions!A:A,">="&DATE(2026,ROW()-17,1),Transactions!A:A,"<"&DATE(2026,ROW()-16,1)) -> 45000 | C23: =SUMIFS(Transactions!E:E,Transactions!B:B,"Expense",Transactions!A:A,">="&DATE(2026,ROW()-17,1),Transactions!A:A,"<"&DATE(2026,ROW()-16,1)) -> 30100 | D23: =SUMIFS(Transactions!E:E,Transactions!B:B,"Savings",Transactions!A:A,">="&DATE(2026,ROW()-17,1),Transactions!A:A,"<"&DATE(2026,ROW()-16,1)) -> 7500 | E23: =B23-C23-D23 -> 7400 | F23: =D23/B23 -> 0.16666667
